AUTHORS
LICENSE
creole/__init__.py
creole/cmdline.py
creole/emitter/__init__.py
creole/emitter/creol2html_emitter.py
creole/emitter/html2creole_emitter.py
creole/emitter/html2rest_emitter.py
creole/emitter/html2textile_emitter.py
creole/exceptions.py
creole/html_tools/__init__.py
creole/html_tools/deentity.py
creole/html_tools/strip_html.py
creole/html_tools/text_tools.py
creole/parser/__init__.py
creole/parser/creol2html_parser.py
creole/parser/creol2html_rules.py
creole/parser/html_parser.py
creole/parser/html_parser_config.py
creole/publish.py
creole/rest_tools/__init__.py
creole/rest_tools/clean_writer.py
creole/rest_tools/pypi_rest2html.py
creole/setup_utils.py
creole/shared/__init__.py
creole/shared/base_emitter.py
creole/shared/diff_utils.py
creole/shared/document_tree.py
creole/shared/example_macros.py
creole/shared/markup_table.py
creole/shared/unknown_tags.py
creole/shared/utils.py
creole/tests/__init__.py
creole/tests/constants.py
creole/tests/test_Makefile.py
creole/tests/test_README.creole
creole/tests/test_TODOs.py
creole/tests/test_cli.py
creole/tests/test_creole2html.py
creole/tests/test_cross_compare_all.py
creole/tests/test_cross_compare_creole.py
creole/tests/test_cross_compare_rest.py
creole/tests/test_cross_compare_textile.py
creole/tests/test_html2creole.py
creole/tests/test_html2rest.py
creole/tests/test_html2textile.py
creole/tests/test_macros.py
creole/tests/test_project_setup.py
creole/tests/test_rest2html.py
creole/tests/test_setup_utils.py
creole/tests/test_subprocess.py
creole/tests/test_utils.py
creole/tests/utils/__init__.py
creole/tests/utils/base_unittest.py
creole/tests/utils/unittest_subprocess.py
creole/tests/utils/utils.py
python_creole_atlassian-1.4.92.dist-info/entry_points.txt
python_creole_atlassian-1.4.92.dist-info/LICENSE
python_creole_atlassian-1.4.92.dist-info/WHEEL
python_creole_atlassian-1.4.92.dist-info/METADATA
python_creole_atlassian-1.4.92.dist-info/RECORD
