Metadata-Version: 2.1
Name: python-creole-atlassian
Version: 1.4.92
Summary: python-creole is an open-source (GPL) markup converter in pure Python for: creole2html, html2creole, html2ReSt, html2textile
Home-page: https://github.com/jedie/python-creole/
License: GPL-3.0-or-later
Keywords: creole,markup,creole2html,html2creole,rest2html,html2rest,html2textile
Author: Jens Diemer
Author-email: python-creole@jensdiemer.de
Requires-Python: >=3.6,<4.0.0
Classifier: Development Status :: 5 - Production/Stable
Classifier: Environment :: Web Environment
Classifier: Intended Audience :: Developers
Classifier: License :: OSI Approved :: GNU General Public License (GPL)
Classifier: License :: OSI Approved :: GNU General Public License v3 or later (GPLv3+)
Classifier: Operating System :: OS Independent
Classifier: Programming Language :: Python
Classifier: Programming Language :: Python :: 3
Classifier: Programming Language :: Python :: 3.6
Classifier: Programming Language :: Python :: 3.7
Classifier: Programming Language :: Python :: 3.8
Classifier: Programming Language :: Python :: 3.9
Classifier: Programming Language :: Python :: Implementation :: PyPy
Classifier: Topic :: Documentation
Classifier: Topic :: Internet :: WWW/HTTP :: Dynamic Content
Classifier: Topic :: Software Development :: Libraries :: Python Modules
Classifier: Topic :: Text Processing :: Markup
Classifier: Topic :: Text Processing :: Markup :: HTML
Classifier: Topic :: Utilities
Requires-Dist: docutils
